md_utils-0.6.0.dist-info/RECORD
md_utils-0.6.0.dist-info/DESCRIPTION.rst
md_utils-0.6.0.dist-info/METADATA
md_utils-0.6.0.dist-info/WHEEL
md_utils-0.6.0.dist-info/entry_points.txt
md_utils-0.6.0.dist-info/metadata.json
md_utils-0.6.0.dist-info/top_level.txt
md_utils/fes_combo.py
md_utils/lammps.py
md_utils/calc_pka.py
md_utils/__init__.py
md_utils/path_bin.py
md_utils/lammps_dist.py
md_utils/md_init.py
md_utils/colvar_to_wham.py
md_utils/calc_split_avg.py
md_utils/wham_split.py
md_utils/wham_rad.py
md_utils/press_dups.py
md_utils/wham_block.py
md_utils/wham.py
md_utils/md_common.py
md_utils/skel/tpl/submit_wham_line.tpl
md_utils/skel/tpl/submit_wham.tpl
md_utils/skel/tpl/submit_wham_part_line.tpl
