Metadata-Version: 2.0
Name: md-utils
Version: 0.6.0
Summary: Utility scripts for MD data
Home-page: https://github.com/cmayes/md_utils
Author: Chris Mayes
Author-email: cmayes@cmayes.com
License: BSD
Keywords: md_utils
Platform: UNKNOWN
Classifier: Development Status :: 4 - Beta
Classifier: Intended Audience :: Science/Research
Classifier: License :: OSI Approved :: BSD License
Classifier: Natural Language :: English
Classifier: Programming Language :: Python :: 2
Classifier: Programming Language :: Python :: 2.7
Classifier: Programming Language :: Python :: 3
Classifier: Programming Language :: Python :: 3.3
Classifier: Programming Language :: Python :: 3.4
Classifier: Topic :: Scientific/Engineering :: Chemistry
Requires-Dist: argparse
Requires-Dist: six
Requires-Dist: numpy
